{
    "rootTask": "0",
    "tasks": [
        {
            "phases": [
                {
                    "creates": [],
                    "dependsOn": [
                        0
                    ],
                    "duration": 0.0008420944213867188,
                    "phaseId": 0,
                    "submits": []
                }
            ],
            "results": [
                {
                    "objectId": 1,
                    "size": 112
                }
            ],
            "taskId": "6ed957660cfa4e7599fcc7237a3e16bb"
        },
        {
            "phases": [
                {
                    "creates": [],
                    "dependsOn": [
                        13,
                        14,
                        11,
                        12
                    ],
                    "duration": 0.012634038925170898,
                    "phaseId": 0,
                    "submits": []
                }
            ],
            "results": [
                {
                    "objectId": 15,
                    "size": 393360
                },
                {
                    "objectId": 16,
                    "size": 112
                },
                {
                    "objectId": 17,
                    "size": 589968
                },
                {
                    "objectId": 18,
                    "size": 120
                }
            ],
            "taskId": "b3020c5ce6b947ffb0df2c8b0b656ee3"
        },
        {
            "phases": [
                {
                    "creates": [],
                    "dependsOn": [
                        23,
                        24,
                        37
                    ],
                    "duration": 0.803386926651001,
                    "phaseId": 0,
                    "submits": []
                }
            ],
            "results": [
                {
                    "objectId": 38,
                    "size": 28
                }
            ],
            "taskId": "b2392d3e0b7e4e6190153cad7d2451fe"
        },
        {
            "phases": [
                {
                    "creates": [],
                    "dependsOn": [
                        25,
                        26,
                        53
                    ],
                    "duration": 0.4837520122528076,
                    "phaseId": 0,
                    "submits": []
                }
            ],
            "results": [
                {
                    "objectId": 54,
                    "size": 28
                }
            ],
            "taskId": "426873a149024338846cab8843652cea"
        },
        {
            "phases": [
                {
                    "creates": [],
                    "dependsOn": [
                        23,
                        24,
                        69
                    ],
                    "duration": 0.5589191913604736,
                    "phaseId": 0,
                    "submits": []
                }
            ],
            "results": [
                {
                    "objectId": 70,
                    "size": 28
                }
            ],
            "taskId": "b64627dabab54258956bcf6bbbadbfe4"
        },
        {
            "phases": [
                {
                    "creates": [],
                    "dependsOn": [
                        23,
                        24,
                        85
                    ],
                    "duration": 0.7456350326538086,
                    "phaseId": 0,
                    "submits": []
                }
            ],
            "results": [
                {
                    "objectId": 86,
                    "size": 28
                }
            ],
            "taskId": "b17d30e910a24d1e8d57bb8798ee36a3"
        },
        {
            "phases": [
                {
                    "creates": [],
                    "dependsOn": [
                        23,
                        24,
                        101
                    ],
                    "duration": 0.6019191741943359,
                    "phaseId": 0,
                    "submits": []
                }
            ],
            "results": [
                {
                    "objectId": 102,
                    "size": 28
                }
            ],
            "taskId": "84339ea03dbe489eacf79091ca66dffd"
        },
        {
            "phases": [
                {
                    "creates": [],
                    "dependsOn": [
                        25,
                        26,
                        45
                    ],
                    "duration": 2.59043288230896,
                    "phaseId": 0,
                    "submits": []
                }
            ],
            "results": [
                {
                    "objectId": 46,
                    "size": 28
                }
            ],
            "taskId": "4d6bb5eb9068478eb5d1aa7b07684423"
        },
        {
            "phases": [
                {
                    "creates": [],
                    "dependsOn": [
                        23,
                        24,
                        61
                    ],
                    "duration": 0.6318318843841553,
                    "phaseId": 0,
                    "submits": []
                }
            ],
            "results": [
                {
                    "objectId": 62,
                    "size": 28
                }
            ],
            "taskId": "7dc780e4442c4560b6ffeb42a6ac01dd"
        },
        {
            "phases": [
                {
                    "creates": [],
                    "dependsOn": [
                        25,
                        26,
                        77
                    ],
                    "duration": 0.7148270606994629,
                    "phaseId": 0,
                    "submits": []
                }
            ],
            "results": [
                {
                    "objectId": 78,
                    "size": 28
                }
            ],
            "taskId": "fde3c8f18e534ce9ab2ad6a1ae672790"
        },
        {
            "phases": [
                {
                    "creates": [],
                    "dependsOn": [
                        25,
                        26,
                        93
                    ],
                    "duration": 0.591533899307251,
                    "phaseId": 0,
                    "submits": []
                }
            ],
            "results": [
                {
                    "objectId": 94,
                    "size": 28
                }
            ],
            "taskId": "228cbf16b55041ee8dc58745cf79e8be"
        },
        {
            "phases": [
                {
                    "creates": [],
                    "dependsOn": [
                        0
                    ],
                    "duration": 0.0012850761413574219,
                    "phaseId": 0,
                    "submits": []
                }
            ],
            "results": [
                {
                    "objectId": 2,
                    "size": 120
                }
            ],
            "taskId": "35b509c95e4e4147b4e52d305d6b493f"
        },
        {
            "phases": [
                {
                    "creates": [],
                    "dependsOn": [
                        9,
                        10,
                        7,
                        8
                    ],
                    "duration": 0.024364948272705078,
                    "phaseId": 0,
                    "submits": []
                }
            ],
            "results": [
                {
                    "objectId": 11,
                    "size": 589968
                },
                {
                    "objectId": 12,
                    "size": 120
                },
                {
                    "objectId": 13,
                    "size": 393360
                },
                {
                    "objectId": 14,
                    "size": 112
                }
            ],
            "taskId": "7c928da3378a437c8685680643f71793"
        },
        {
            "phases": [
                {
                    "creates": [],
                    "dependsOn": [
                        21,
                        22,
                        19,
                        20
                    ],
                    "duration": 0.0068171024322509766,
                    "phaseId": 0,
                    "submits": []
                }
            ],
            "results": [
                {
                    "objectId": 23,
                    "size": 589968
                },
                {
                    "objectId": 24,
                    "size": 120
                },
                {
                    "objectId": 25,
                    "size": 393360
                },
                {
                    "objectId": 26,
                    "size": 112
                }
            ],
            "taskId": "142b2f12cd7e4f1883d1d9fc49c52ec9"
        },
        {
            "phases": [
                {
                    "creates": [],
                    "dependsOn": [
                        25,
                        26,
                        4,
                        37
                    ],
                    "duration": 47.09123706817627,
                    "phaseId": 0,
                    "submits": []
                }
            ],
            "results": [
                {
                    "objectId": 41,
                    "size": 200
                }
            ],
            "taskId": "c3b7c8d50e584d6c9d828c0fb25d4dc8"
        },
        {
            "phases": [
                {
                    "creates": [],
                    "dependsOn": [
                        23,
                        24,
                        4,
                        45
                    ],
                    "duration": 39.73188519477844,
                    "phaseId": 0,
                    "submits": []
                }
            ],
            "results": [
                {
                    "objectId": 47,
                    "size": 200
                }
            ],
            "taskId": "785c8957af484b5b97bc5a4679a4a9b7"
        },
        {
            "phases": [
                {
                    "creates": [],
                    "dependsOn": [
                        23,
                        24,
                        4,
                        53
                    ],
                    "duration": 43.07347917556763,
                    "phaseId": 0,
                    "submits": []
                }
            ],
            "results": [
                {
                    "objectId": 60,
                    "size": 200
                }
            ],
            "taskId": "838f20960aa044628951895ae0700a89"
        },
        {
            "phases": [
                {
                    "creates": [],
                    "dependsOn": [
                        23,
                        24,
                        4,
                        61
                    ],
                    "duration": 44.51851296424866,
                    "phaseId": 0,
                    "submits": []
                }
            ],
            "results": [
                {
                    "objectId": 68,
                    "size": 200
                }
            ],
            "taskId": "eaf2e7f088554fc4b0ae35264c2f58b3"
        },
        {
            "phases": [
                {
                    "creates": [],
                    "dependsOn": [
                        23,
                        24,
                        4,
                        69
                    ],
                    "duration": 45.22859787940979,
                    "phaseId": 0,
                    "submits": []
                }
            ],
            "results": [
                {
                    "objectId": 76,
                    "size": 200
                }
            ],
            "taskId": "34367f6722944a608cee3d8b3f8ddd81"
        },
        {
            "phases": [
                {
                    "creates": [],
                    "dependsOn": [
                        25,
                        26,
                        4,
                        77
                    ],
                    "duration": 45.619412899017334,
                    "phaseId": 0,
                    "submits": []
                }
            ],
            "results": [
                {
                    "objectId": 81,
                    "size": 200
                }
            ],
            "taskId": "8ca8c1af8ce44438a4cb53ae8082aa76"
        },
        {
            "phases": [
                {
                    "creates": [],
                    "dependsOn": [
                        25,
                        26,
                        4,
                        85
                    ],
                    "duration": 45.66951084136963,
                    "phaseId": 0,
                    "submits": []
                }
            ],
            "results": [
                {
                    "objectId": 88,
                    "size": 200
                }
            ],
            "taskId": "8b56b5ae40384b9fab6efe38c807d80a"
        },
        {
            "phases": [
                {
                    "creates": [],
                    "dependsOn": [
                        25,
                        26,
                        4,
                        93
                    ],
                    "duration": 46.0092408657074,
                    "phaseId": 0,
                    "submits": []
                }
            ],
            "results": [
                {
                    "objectId": 95,
                    "size": 200
                }
            ],
            "taskId": "34ec00f9971648ce859ea3597f29fc0d"
        },
        {
            "phases": [
                {
                    "creates": [],
                    "dependsOn": [
                        23,
                        24,
                        4,
                        101
                    ],
                    "duration": 45.24528098106384,
                    "phaseId": 0,
                    "submits": []
                }
            ],
            "results": [
                {
                    "objectId": 103,
                    "size": 200
                }
            ],
            "taskId": "eeacf33af5db47bf924c6884419155f6"
        },
        {
            "phases": [
                {
                    "creates": [
                        {
                            "objectId": 33,
                            "size": 144,
                            "timeOffset": 0.0031278133392333984
                        },
                        {
                            "objectId": 35,
                            "size": 144,
                            "timeOffset": 0.009130001068115234
                        }
                    ],
                    "dependsOn": [],
                    "duration": 0.010949850082397461,
                    "phaseId": 0,
                    "submits": [
                        {
                            "taskId": "1c6c13e8ccfb4e4e8d042ca145e222af",
                            "timeOffset": 0.0047419071197509766
                        },
                        {
                            "taskId": "5bb70285228548af9e520162e897eb94",
                            "timeOffset": 0.010614871978759766
                        }
                    ]
                },
                {
                    "creates": [
                        {
                            "objectId": 33,
                            "size": 144,
                            "timeOffset": 0.0031278133392333984
                        },
                        {
                            "objectId": 35,
                            "size": 144,
                            "timeOffset": 0.009130001068115234
                        }
                    ],
                    "dependsOn": [],
                    "duration": 0.015228986740112305,
                    "phaseId": 0,
                    "submits": [
                        {
                            "taskId": "1c6c13e8ccfb4e4e8d042ca145e222af",
                            "timeOffset": 0.0047419071197509766
                        },
                        {
                            "taskId": "5bb70285228548af9e520162e897eb94",
                            "timeOffset": 0.010614871978759766
                        }
                    ]
                }
            ],
            "results": [
                {
                    "objectId": 32,
                    "size": 24
                }
            ],
            "taskId": "71938e011ec54fc6a5b9672c08d83bc3"
        },
        {
            "phases": [
                {
                    "creates": [],
                    "dependsOn": [
                        25,
                        26,
                        4,
                        37
                    ],
                    "duration": 44.68036484718323,
                    "phaseId": 0,
                    "submits": []
                }
            ],
            "results": [
                {
                    "objectId": 43,
                    "size": 200
                }
            ],
            "taskId": "9ab64368d7fb44fdb0b30afa96b32944"
        },
        {
            "phases": [
                {
                    "creates": [],
                    "dependsOn": [
                        23,
                        24,
                        4,
                        45
                    ],
                    "duration": 45.76172184944153,
                    "phaseId": 0,
                    "submits": []
                }
            ],
            "results": [
                {
                    "objectId": 52,
                    "size": 200
                }
            ],
            "taskId": "a7c7462cd0cf45adbe5a3a1c94f6d6bf"
        },
        {
            "phases": [
                {
                    "creates": [],
                    "dependsOn": [
                        23,
                        24,
                        4,
                        53
                    ],
                    "duration": 45.522504806518555,
                    "phaseId": 0,
                    "submits": []
                }
            ],
            "results": [
                {
                    "objectId": 57,
                    "size": 200
                }
            ],
            "taskId": "7e664e7b3cf047c593a870e24ee46565"
        },
        {
            "phases": [
                {
                    "creates": [],
                    "dependsOn": [
                        25,
                        26,
                        4,
                        61
                    ],
                    "duration": 45.3793740272522,
                    "phaseId": 0,
                    "submits": []
                }
            ],
            "results": [
                {
                    "objectId": 67,
                    "size": 200
                }
            ],
            "taskId": "501b34271aa1445987e20d4599b76442"
        },
        {
            "phases": [
                {
                    "creates": [],
                    "dependsOn": [
                        25,
                        26,
                        4,
                        69
                    ],
                    "duration": 44.82464289665222,
                    "phaseId": 0,
                    "submits": []
                }
            ],
            "results": [
                {
                    "objectId": 71,
                    "size": 200
                }
            ],
            "taskId": "e065f0cee7d14de0a02b408fe4ccb3f3"
        },
        {
            "phases": [
                {
                    "creates": [],
                    "dependsOn": [
                        25,
                        26,
                        4,
                        77
                    ],
                    "duration": 45.65129518508911,
                    "phaseId": 0,
                    "submits": []
                }
            ],
            "results": [
                {
                    "objectId": 83,
                    "size": 200
                }
            ],
            "taskId": "783e1120b48c468b87161658d8100f54"
        },
        {
            "phases": [
                {
                    "creates": [],
                    "dependsOn": [
                        25,
                        26,
                        4,
                        85
                    ],
                    "duration": 45.41324186325073,
                    "phaseId": 0,
                    "submits": []
                }
            ],
            "results": [
                {
                    "objectId": 87,
                    "size": 200
                }
            ],
            "taskId": "a95aa32546f74fa89029f97f7d47a917"
        },
        {
            "phases": [
                {
                    "creates": [],
                    "dependsOn": [
                        25,
                        26,
                        4,
                        93
                    ],
                    "duration": 44.82166910171509,
                    "phaseId": 0,
                    "submits": []
                }
            ],
            "results": [
                {
                    "objectId": 98,
                    "size": 200
                }
            ],
            "taskId": "ee697196e1434913adcc018ab4d36b12"
        },
        {
            "phases": [
                {
                    "creates": [],
                    "dependsOn": [
                        23,
                        24,
                        4,
                        101
                    ],
                    "duration": 45.434542179107666,
                    "phaseId": 0,
                    "submits": []
                }
            ],
            "results": [
                {
                    "objectId": 107,
                    "size": 200
                }
            ],
            "taskId": "d6c80cf590ca4d25bfff856738a6573d"
        },
        {
            "phases": [
                {
                    "creates": [
                        {
                            "objectId": 0,
                            "size": 280,
                            "timeOffset": 0.485396146774292
                        },
                        {
                            "objectId": 3,
                            "size": 104,
                            "timeOffset": 0.5066499710083008
                        },
                        {
                            "objectId": 5,
                            "size": 393360,
                            "timeOffset": 0.5104420185089111
                        },
                        {
                            "objectId": 6,
                            "size": 589968,
                            "timeOffset": 0.513808012008667
                        },
                        {
                            "objectId": 37,
                            "size": 200,
                            "timeOffset": 3.2781081199645996
                        }
                    ],
                    "dependsOn": [],
                    "duration": 3.288743019104004,
                    "phaseId": 0,
                    "submits": [
                        {
                            "taskId": "6ed957660cfa4e7599fcc7237a3e16bb",
                            "timeOffset": 0.500493049621582
                        },
                        {
                            "taskId": "35b509c95e4e4147b4e52d305d6b493f",
                            "timeOffset": 0.5017940998077393
                        },
                        {
                            "taskId": "6b638df85f52414ea908c8b323e7138d",
                            "timeOffset": 0.5079920291900635
                        },
                        {
                            "taskId": "ff44bc33ce8b4cf3aff21f61acb7f671",
                            "timeOffset": 0.5153119564056396
                        },
                        {
                            "taskId": "7c928da3378a437c8685680643f71793",
                            "timeOffset": 0.5175249576568604
                        },
                        {
                            "taskId": "b3020c5ce6b947ffb0df2c8b0b656ee3",
                            "timeOffset": 0.5196850299835205
                        },
                        {
                            "taskId": "3783d559a7864d7c9c3431eeb55505d8",
                            "timeOffset": 0.5218150615692139
                        },
                        {
                            "taskId": "142b2f12cd7e4f1883d1d9fc49c52ec9",
                            "timeOffset": 0.5240190029144287
                        },
                        {
                            "taskId": "b2392d3e0b7e4e6190153cad7d2451fe",
                            "timeOffset": 3.2798540592193604
                        },
                        {
                            "taskId": "4abf9255553148adb791976dddc1ff21",
                            "timeOffset": 3.281233072280884
                        },
                        {
                            "taskId": "1a8adc0f17884a28bffba2347ef426a2",
                            "timeOffset": 3.282526969909668
                        },
                        {
                            "taskId": "c3b7c8d50e584d6c9d828c0fb25d4dc8",
                            "timeOffset": 3.2838571071624756
                        },
                        {
                            "taskId": "db7c18b054dd4d479aa6b1f3e57fee5d",
                            "timeOffset": 3.285290002822876
                        },
                        {
                            "taskId": "9ab64368d7fb44fdb0b30afa96b32944",
                            "timeOffset": 3.2868220806121826
                        },
                        {
                            "taskId": "aaca4eb03dbf4ae797217f6ac0939a50",
                            "timeOffset": 3.288583993911743
                        }
                    ]
                },
                {
                    "creates": [
                        {
                            "objectId": 45,
                            "size": 200,
                            "timeOffset": 48.09272599220276
                        }
                    ],
                    "dependsOn": [
                        38
                    ],
                    "duration": 0.0006649494171142578,
                    "phaseId": 1,
                    "submits": [
                        {
                            "taskId": "4d6bb5eb9068478eb5d1aa7b07684423",
                            "timeOffset": 48.11934804916382
                        },
                        {
                            "taskId": "785c8957af484b5b97bc5a4679a4a9b7",
                            "timeOffset": 48.121110916137695
                        },
                        {
                            "taskId": "a2ee2a0688e04b89808f9c9be20e1841",
                            "timeOffset": 48.12244892120361
                        },
                        {
                            "taskId": "97eda6a1d0a04fdeaae4e6f21c72f9bd",
                            "timeOffset": 48.123831033706665
                        },
                        {
                            "taskId": "7735ed259cec4d98a4f963baf2e31086",
                            "timeOffset": 48.125144958496094
                        },
                        {
                            "taskId": "ed31e420c9c74ffc95bce58190179129",
                            "timeOffset": 48.12672996520996
                        },
                        {
                            "taskId": "a7c7462cd0cf45adbe5a3a1c94f6d6bf",
                            "timeOffset": 48.12836694717407
                        }
                    ]
                },
                {
                    "creates": [
                        {
                            "objectId": 45,
                            "size": 200,
                            "timeOffset": 48.09272599220276
                        }
                    ],
                    "dependsOn": [
                        38
                    ],
                    "duration": 48.12852907180786,
                    "phaseId": 1,
                    "submits": [
                        {
                            "taskId": "4d6bb5eb9068478eb5d1aa7b07684423",
                            "timeOffset": 48.11934804916382
                        },
                        {
                            "taskId": "785c8957af484b5b97bc5a4679a4a9b7",
                            "timeOffset": 48.121110916137695
                        },
                        {
                            "taskId": "a2ee2a0688e04b89808f9c9be20e1841",
                            "timeOffset": 48.12244892120361
                        },
                        {
                            "taskId": "97eda6a1d0a04fdeaae4e6f21c72f9bd",
                            "timeOffset": 48.123831033706665
                        },
                        {
                            "taskId": "7735ed259cec4d98a4f963baf2e31086",
                            "timeOffset": 48.125144958496094
                        },
                        {
                            "taskId": "ed31e420c9c74ffc95bce58190179129",
                            "timeOffset": 48.12672996520996
                        },
                        {
                            "taskId": "a7c7462cd0cf45adbe5a3a1c94f6d6bf",
                            "timeOffset": 48.12836694717407
                        }
                    ]
                },
                {
                    "creates": [
                        {
                            "objectId": 53,
                            "size": 200,
                            "timeOffset": 45.260952949523926
                        }
                    ],
                    "dependsOn": [
                        46
                    ],
                    "duration": 0.0005471706390380859,
                    "phaseId": 2,
                    "submits": [
                        {
                            "taskId": "426873a149024338846cab8843652cea",
                            "timeOffset": 45.282780170440674
                        },
                        {
                            "taskId": "506095e4b6b847cb9a88090865dfc0c6",
                            "timeOffset": 45.28455710411072
                        },
                        {
                            "taskId": "d5571dca39a14c3caf57fe919dfe6ff1",
                            "timeOffset": 45.285804986953735
                        },
                        {
                            "taskId": "7e664e7b3cf047c593a870e24ee46565",
                            "timeOffset": 45.28762602806091
                        },
                        {
                            "taskId": "7510f632a5534d01b35d9bdfa882df53",
                            "timeOffset": 45.2890260219574
                        },
                        {
                            "taskId": "f9c0715becdf44629192d34b97c191d0",
                            "timeOffset": 45.29077410697937
                        },
                        {
                            "taskId": "838f20960aa044628951895ae0700a89",
                            "timeOffset": 45.292585134506226
                        }
                    ]
                },
                {
                    "creates": [
                        {
                            "objectId": 53,
                            "size": 200,
                            "timeOffset": 45.260952949523926
                        }
                    ],
                    "dependsOn": [
                        46
                    ],
                    "duration": 45.29280495643616,
                    "phaseId": 2,
                    "submits": [
                        {
                            "taskId": "426873a149024338846cab8843652cea",
                            "timeOffset": 45.282780170440674
                        },
                        {
                            "taskId": "506095e4b6b847cb9a88090865dfc0c6",
                            "timeOffset": 45.28455710411072
                        },
                        {
                            "taskId": "d5571dca39a14c3caf57fe919dfe6ff1",
                            "timeOffset": 45.285804986953735
                        },
                        {
                            "taskId": "7e664e7b3cf047c593a870e24ee46565",
                            "timeOffset": 45.28762602806091
                        },
                        {
                            "taskId": "7510f632a5534d01b35d9bdfa882df53",
                            "timeOffset": 45.2890260219574
                        },
                        {
                            "taskId": "f9c0715becdf44629192d34b97c191d0",
                            "timeOffset": 45.29077410697937
                        },
                        {
                            "taskId": "838f20960aa044628951895ae0700a89",
                            "timeOffset": 45.292585134506226
                        }
                    ]
                },
                {
                    "creates": [
                        {
                            "objectId": 61,
                            "size": 200,
                            "timeOffset": 47.38641905784607
                        }
                    ],
                    "dependsOn": [
                        54
                    ],
                    "duration": 0.0005509853363037109,
                    "phaseId": 3,
                    "submits": [
                        {
                            "taskId": "7dc780e4442c4560b6ffeb42a6ac01dd",
                            "timeOffset": 47.411431074142456
                        },
                        {
                            "taskId": "f09fb160074b4e698af7a872bb966072",
                            "timeOffset": 47.41341710090637
                        },
                        {
                            "taskId": "b46bd7d4e1eb427e8f6ddee8eb74a6ce",
                            "timeOffset": 47.414796113967896
                        },
                        {
                            "taskId": "c7a0061d87a24fc790dd7ae1da132676",
                            "timeOffset": 47.416139125823975
                        },
                        {
                            "taskId": "5af870f295f14275800422b8d6278505",
                            "timeOffset": 47.41759014129639
                        },
                        {
                            "taskId": "501b34271aa1445987e20d4599b76442",
                            "timeOffset": 47.41923403739929
                        },
                        {
                            "taskId": "eaf2e7f088554fc4b0ae35264c2f58b3",
                            "timeOffset": 47.42103600502014
                        }
                    ]
                },
                {
                    "creates": [
                        {
                            "objectId": 61,
                            "size": 200,
                            "timeOffset": 47.38641905784607
                        }
                    ],
                    "dependsOn": [
                        54
                    ],
                    "duration": 47.42123794555664,
                    "phaseId": 3,
                    "submits": [
                        {
                            "taskId": "7dc780e4442c4560b6ffeb42a6ac01dd",
                            "timeOffset": 47.411431074142456
                        },
                        {
                            "taskId": "f09fb160074b4e698af7a872bb966072",
                            "timeOffset": 47.41341710090637
                        },
                        {
                            "taskId": "b46bd7d4e1eb427e8f6ddee8eb74a6ce",
                            "timeOffset": 47.414796113967896
                        },
                        {
                            "taskId": "c7a0061d87a24fc790dd7ae1da132676",
                            "timeOffset": 47.416139125823975
                        },
                        {
                            "taskId": "5af870f295f14275800422b8d6278505",
                            "timeOffset": 47.41759014129639
                        },
                        {
                            "taskId": "501b34271aa1445987e20d4599b76442",
                            "timeOffset": 47.41923403739929
                        },
                        {
                            "taskId": "eaf2e7f088554fc4b0ae35264c2f58b3",
                            "timeOffset": 47.42103600502014
                        }
                    ]
                },
                {
                    "creates": [
                        {
                            "objectId": 69,
                            "size": 200,
                            "timeOffset": 46.727055072784424
                        }
                    ],
                    "dependsOn": [
                        62
                    ],
                    "duration": 0.0006890296936035156,
                    "phaseId": 4,
                    "submits": [
                        {
                            "taskId": "b64627dabab54258956bcf6bbbadbfe4",
                            "timeOffset": 46.752501010894775
                        },
                        {
                            "taskId": "e065f0cee7d14de0a02b408fe4ccb3f3",
                            "timeOffset": 46.75420904159546
                        },
                        {
                            "taskId": "a04dbc3ed086426e9aae5424e0e02c36",
                            "timeOffset": 46.75554013252258
                        },
                        {
                            "taskId": "08b9089d0ad74412aaf0fa456743f38e",
                            "timeOffset": 46.75696516036987
                        },
                        {
                            "taskId": "ae297a0d676345a4a35d77736f1fb057",
                            "timeOffset": 46.758265018463135
                        },
                        {
                            "taskId": "be5ac2f2d4e24f1681e0143757a6d156",
                            "timeOffset": 46.75965213775635
                        },
                        {
                            "taskId": "34367f6722944a608cee3d8b3f8ddd81",
                            "timeOffset": 46.761183977127075
                        }
                    ]
                },
                {
                    "creates": [
                        {
                            "objectId": 69,
                            "size": 200,
                            "timeOffset": 46.727055072784424
                        }
                    ],
                    "dependsOn": [
                        62
                    ],
                    "duration": 46.76130294799805,
                    "phaseId": 4,
                    "submits": [
                        {
                            "taskId": "b64627dabab54258956bcf6bbbadbfe4",
                            "timeOffset": 46.752501010894775
                        },
                        {
                            "taskId": "e065f0cee7d14de0a02b408fe4ccb3f3",
                            "timeOffset": 46.75420904159546
                        },
                        {
                            "taskId": "a04dbc3ed086426e9aae5424e0e02c36",
                            "timeOffset": 46.75554013252258
                        },
                        {
                            "taskId": "08b9089d0ad74412aaf0fa456743f38e",
                            "timeOffset": 46.75696516036987
                        },
                        {
                            "taskId": "ae297a0d676345a4a35d77736f1fb057",
                            "timeOffset": 46.758265018463135
                        },
                        {
                            "taskId": "be5ac2f2d4e24f1681e0143757a6d156",
                            "timeOffset": 46.75965213775635
                        },
                        {
                            "taskId": "34367f6722944a608cee3d8b3f8ddd81",
                            "timeOffset": 46.761183977127075
                        }
                    ]
                },
                {
                    "creates": [
                        {
                            "objectId": 77,
                            "size": 200,
                            "timeOffset": 47.220134019851685
                        }
                    ],
                    "dependsOn": [
                        70
                    ],
                    "duration": 0.0005278587341308594,
                    "phaseId": 5,
                    "submits": [
                        {
                            "taskId": "fde3c8f18e534ce9ab2ad6a1ae672790",
                            "timeOffset": 47.24448299407959
                        },
                        {
                            "taskId": "947ad47a971947c0ba64e925e84b4135",
                            "timeOffset": 47.2465078830719
                        },
                        {
                            "taskId": "57041dfd111440bf9364fadc81385f0e",
                            "timeOffset": 47.24794888496399
                        },
                        {
                            "taskId": "8ca8c1af8ce44438a4cb53ae8082aa76",
                            "timeOffset": 47.24934101104736
                        },
                        {
                            "taskId": "2c791430e21d48dea0a05f98c102d3ed",
                            "timeOffset": 47.25103402137756
                        },
                        {
                            "taskId": "783e1120b48c468b87161658d8100f54",
                            "timeOffset": 47.25252294540405
                        },
                        {
                            "taskId": "fcfa11e723f34e9ca47abe94443f8325",
                            "timeOffset": 47.25403881072998
                        }
                    ]
                },
                {
                    "creates": [
                        {
                            "objectId": 77,
                            "size": 200,
                            "timeOffset": 47.220134019851685
                        }
                    ],
                    "dependsOn": [
                        70
                    ],
                    "duration": 47.2542188167572,
                    "phaseId": 5,
                    "submits": [
                        {
                            "taskId": "fde3c8f18e534ce9ab2ad6a1ae672790",
                            "timeOffset": 47.24448299407959
                        },
                        {
                            "taskId": "947ad47a971947c0ba64e925e84b4135",
                            "timeOffset": 47.2465078830719
                        },
                        {
                            "taskId": "57041dfd111440bf9364fadc81385f0e",
                            "timeOffset": 47.24794888496399
                        },
                        {
                            "taskId": "8ca8c1af8ce44438a4cb53ae8082aa76",
                            "timeOffset": 47.24934101104736
                        },
                        {
                            "taskId": "2c791430e21d48dea0a05f98c102d3ed",
                            "timeOffset": 47.25103402137756
                        },
                        {
                            "taskId": "783e1120b48c468b87161658d8100f54",
                            "timeOffset": 47.25252294540405
                        },
                        {
                            "taskId": "fcfa11e723f34e9ca47abe94443f8325",
                            "timeOffset": 47.25403881072998
                        }
                    ]
                },
                {
                    "creates": [
                        {
                            "objectId": 85,
                            "size": 200,
                            "timeOffset": 46.90866994857788
                        }
                    ],
                    "dependsOn": [
                        78
                    ],
                    "duration": 0.0002391338348388672,
                    "phaseId": 6,
                    "submits": [
                        {
                            "taskId": "b17d30e910a24d1e8d57bb8798ee36a3",
                            "timeOffset": 46.934704065322876
                        },
                        {
                            "taskId": "a95aa32546f74fa89029f97f7d47a917",
                            "timeOffset": 46.93643498420715
                        },
                        {
                            "taskId": "8b56b5ae40384b9fab6efe38c807d80a",
                            "timeOffset": 46.93778610229492
                        },
                        {
                            "taskId": "ce6a68fe828546c4b20f0f2f1bf07565",
                            "timeOffset": 46.93923497200012
                        },
                        {
                            "taskId": "2d7cdb8215804b9e890ee613f6ca2fa0",
                            "timeOffset": 46.94064903259277
                        },
                        {
                            "taskId": "eb3614eda45f4fc986132a369670a445",
                            "timeOffset": 46.941978931427
                        },
                        {
                            "taskId": "4e7ca2b98ef74321b145d346af21aa02",
                            "timeOffset": 46.94349002838135
                        }
                    ]
                },
                {
                    "creates": [
                        {
                            "objectId": 85,
                            "size": 200,
                            "timeOffset": 46.90866994857788
                        }
                    ],
                    "dependsOn": [
                        78
                    ],
                    "duration": 46.94363212585449,
                    "phaseId": 6,
                    "submits": [
                        {
                            "taskId": "b17d30e910a24d1e8d57bb8798ee36a3",
                            "timeOffset": 46.934704065322876
                        },
                        {
                            "taskId": "a95aa32546f74fa89029f97f7d47a917",
                            "timeOffset": 46.93643498420715
                        },
                        {
                            "taskId": "8b56b5ae40384b9fab6efe38c807d80a",
                            "timeOffset": 46.93778610229492
                        },
                        {
                            "taskId": "ce6a68fe828546c4b20f0f2f1bf07565",
                            "timeOffset": 46.93923497200012
                        },
                        {
                            "taskId": "2d7cdb8215804b9e890ee613f6ca2fa0",
                            "timeOffset": 46.94064903259277
                        },
                        {
                            "taskId": "eb3614eda45f4fc986132a369670a445",
                            "timeOffset": 46.941978931427
                        },
                        {
                            "taskId": "4e7ca2b98ef74321b145d346af21aa02",
                            "timeOffset": 46.94349002838135
                        }
                    ]
                },
                {
                    "creates": [
                        {
                            "objectId": 93,
                            "size": 200,
                            "timeOffset": 46.90534520149231
                        }
                    ],
                    "dependsOn": [
                        86
                    ],
                    "duration": 0.0006880760192871094,
                    "phaseId": 7,
                    "submits": [
                        {
                            "taskId": "228cbf16b55041ee8dc58745cf79e8be",
                            "timeOffset": 46.93126606941223
                        },
                        {
                            "taskId": "34ec00f9971648ce859ea3597f29fc0d",
                            "timeOffset": 46.93294310569763
                        },
                        {
                            "taskId": "ecf37c92c5cc44828164ae3a9b630e72",
                            "timeOffset": 46.93420600891113
                        },
                        {
                            "taskId": "e5b03b43745e4c5594de454a42b7566f",
                            "timeOffset": 46.93549919128418
                        },
                        {
                            "taskId": "ee697196e1434913adcc018ab4d36b12",
                            "timeOffset": 46.936782121658325
                        },
                        {
                            "taskId": "c70b7a6122294025a9890cefd8497710",
                            "timeOffset": 46.93829107284546
                        },
                        {
                            "taskId": "470b6c27caa74fd9894a8bddae88faa0",
                            "timeOffset": 46.93997621536255
                        }
                    ]
                },
                {
                    "creates": [
                        {
                            "objectId": 93,
                            "size": 200,
                            "timeOffset": 46.90534520149231
                        }
                    ],
                    "dependsOn": [
                        86
                    ],
                    "duration": 46.9401421546936,
                    "phaseId": 7,
                    "submits": [
                        {
                            "taskId": "228cbf16b55041ee8dc58745cf79e8be",
                            "timeOffset": 46.93126606941223
                        },
                        {
                            "taskId": "34ec00f9971648ce859ea3597f29fc0d",
                            "timeOffset": 46.93294310569763
                        },
                        {
                            "taskId": "ecf37c92c5cc44828164ae3a9b630e72",
                            "timeOffset": 46.93420600891113
                        },
                        {
                            "taskId": "e5b03b43745e4c5594de454a42b7566f",
                            "timeOffset": 46.93549919128418
                        },
                        {
                            "taskId": "ee697196e1434913adcc018ab4d36b12",
                            "timeOffset": 46.936782121658325
                        },
                        {
                            "taskId": "c70b7a6122294025a9890cefd8497710",
                            "timeOffset": 46.93829107284546
                        },
                        {
                            "taskId": "470b6c27caa74fd9894a8bddae88faa0",
                            "timeOffset": 46.93997621536255
                        }
                    ]
                },
                {
                    "creates": [
                        {
                            "objectId": 101,
                            "size": 200,
                            "timeOffset": 47.4174280166626
                        }
                    ],
                    "dependsOn": [
                        94
                    ],
                    "duration": 0.0005431175231933594,
                    "phaseId": 8,
                    "submits": [
                        {
                            "taskId": "84339ea03dbe489eacf79091ca66dffd",
                            "timeOffset": 47.44264316558838
                        },
                        {
                            "taskId": "eeacf33af5db47bf924c6884419155f6",
                            "timeOffset": 47.44446611404419
                        },
                        {
                            "taskId": "799375bfdf3c41aeb0a3e19730cb2561",
                            "timeOffset": 47.44594216346741
                        },
                        {
                            "taskId": "df87ddc7e6824e5cb1319034269f547e",
                            "timeOffset": 47.44746208190918
                        },
                        {
                            "taskId": "5f11921148a04180a5e881825fb9f1f9",
                            "timeOffset": 47.448979139328
                        },
                        {
                            "taskId": "d6c80cf590ca4d25bfff856738a6573d",
                            "timeOffset": 47.45083212852478
                        },
                        {
                            "taskId": "f954519ed4304bc1a7228448136bb1c8",
                            "timeOffset": 47.45293712615967
                        }
                    ]
                },
                {
                    "creates": [
                        {
                            "objectId": 101,
                            "size": 200,
                            "timeOffset": 47.4174280166626
                        }
                    ],
                    "dependsOn": [
                        94
                    ],
                    "duration": 47.45316195487976,
                    "phaseId": 8,
                    "submits": [
                        {
                            "taskId": "84339ea03dbe489eacf79091ca66dffd",
                            "timeOffset": 47.44264316558838
                        },
                        {
                            "taskId": "eeacf33af5db47bf924c6884419155f6",
                            "timeOffset": 47.44446611404419
                        },
                        {
                            "taskId": "799375bfdf3c41aeb0a3e19730cb2561",
                            "timeOffset": 47.44594216346741
                        },
                        {
                            "taskId": "df87ddc7e6824e5cb1319034269f547e",
                            "timeOffset": 47.44746208190918
                        },
                        {
                            "taskId": "5f11921148a04180a5e881825fb9f1f9",
                            "timeOffset": 47.448979139328
                        },
                        {
                            "taskId": "d6c80cf590ca4d25bfff856738a6573d",
                            "timeOffset": 47.45083212852478
                        },
                        {
                            "taskId": "f954519ed4304bc1a7228448136bb1c8",
                            "timeOffset": 47.45293712615967
                        }
                    ]
                },
                {
                    "creates": [],
                    "dependsOn": [
                        102
                    ],
                    "duration": 0.0005841255187988281,
                    "phaseId": 9,
                    "submits": []
                },
                {
                    "creates": [],
                    "dependsOn": [
                        102
                    ],
                    "duration": 46.83775305747986,
                    "phaseId": 9,
                    "submits": []
                }
            ],
            "results": [],
            "taskId": "0"
        },
        {
            "phases": [
                {
                    "creates": [],
                    "dependsOn": [],
                    "duration": 0.004913806915283203,
                    "phaseId": 0,
                    "submits": []
                }
            ],
            "results": [
                {
                    "objectId": 28,
                    "size": 1572992
                }
            ],
            "taskId": "e235c8d23feb40e4a922c3feaddde7bd"
        },
        {
            "phases": [
                {
                    "creates": [],
                    "dependsOn": [],
                    "duration": 0.001010894775390625,
                    "phaseId": 0,
                    "submits": []
                }
            ],
            "results": [
                {
                    "objectId": 34,
                    "size": 88
                }
            ],
            "taskId": "1c6c13e8ccfb4e4e8d042ca145e222af"
        },
        {
            "phases": [
                {
                    "creates": [],
                    "dependsOn": [
                        1,
                        2
                    ],
                    "duration": 0.007684946060180664,
                    "phaseId": 0,
                    "submits": []
                }
            ],
            "results": [
                {
                    "objectId": 7,
                    "size": 393360
                },
                {
                    "objectId": 8,
                    "size": 112
                },
                {
                    "objectId": 9,
                    "size": 589968
                },
                {
                    "objectId": 10,
                    "size": 120
                }
            ],
            "taskId": "ff44bc33ce8b4cf3aff21f61acb7f671"
        },
        {
            "phases": [
                {
                    "creates": [],
                    "dependsOn": [
                        15,
                        16,
                        17,
                        18
                    ],
                    "duration": 0.009086132049560547,
                    "phaseId": 0,
                    "submits": []
                }
            ],
            "results": [
                {
                    "objectId": 19,
                    "size": 393360
                },
                {
                    "objectId": 20,
                    "size": 112
                },
                {
                    "objectId": 21,
                    "size": 589968
                },
                {
                    "objectId": 22,
                    "size": 120
                }
            ],
            "taskId": "3783d559a7864d7c9c3431eeb55505d8"
        },
        {
            "phases": [
                {
                    "creates": [],
                    "dependsOn": [
                        23,
                        24,
                        4,
                        37
                    ],
                    "duration": 45.97754788398743,
                    "phaseId": 0,
                    "submits": []
                }
            ],
            "results": [
                {
                    "objectId": 42,
                    "size": 200
                }
            ],
            "taskId": "db7c18b054dd4d479aa6b1f3e57fee5d"
        },
        {
            "phases": [
                {
                    "creates": [],
                    "dependsOn": [
                        25,
                        26,
                        4,
                        45
                    ],
                    "duration": 45.76738691329956,
                    "phaseId": 0,
                    "submits": []
                }
            ],
            "results": [
                {
                    "objectId": 50,
                    "size": 200
                }
            ],
            "taskId": "7735ed259cec4d98a4f963baf2e31086"
        },
        {
            "phases": [
                {
                    "creates": [],
                    "dependsOn": [
                        23,
                        24,
                        4,
                        53
                    ],
                    "duration": 45.626243114471436,
                    "phaseId": 0,
                    "submits": []
                }
            ],
            "results": [
                {
                    "objectId": 56,
                    "size": 200
                }
            ],
            "taskId": "d5571dca39a14c3caf57fe919dfe6ff1"
        },
        {
            "phases": [
                {
                    "creates": [],
                    "dependsOn": [
                        25,
                        26,
                        4,
                        61
                    ],
                    "duration": 45.214065074920654,
                    "phaseId": 0,
                    "submits": []
                }
            ],
            "results": [
                {
                    "objectId": 66,
                    "size": 200
                }
            ],
            "taskId": "5af870f295f14275800422b8d6278505"
        },
        {
            "phases": [
                {
                    "creates": [],
                    "dependsOn": [
                        25,
                        26,
                        4,
                        69
                    ],
                    "duration": 45.49693703651428,
                    "phaseId": 0,
                    "submits": []
                }
            ],
            "results": [
                {
                    "objectId": 73,
                    "size": 200
                }
            ],
            "taskId": "08b9089d0ad74412aaf0fa456743f38e"
        },
        {
            "phases": [
                {
                    "creates": [],
                    "dependsOn": [
                        25,
                        26,
                        4,
                        77
                    ],
                    "duration": 43.25505805015564,
                    "phaseId": 0,
                    "submits": []
                }
            ],
            "results": [
                {
                    "objectId": 79,
                    "size": 200
                }
            ],
            "taskId": "947ad47a971947c0ba64e925e84b4135"
        },
        {
            "phases": [
                {
                    "creates": [],
                    "dependsOn": [
                        23,
                        24,
                        4,
                        85
                    ],
                    "duration": 44.631800174713135,
                    "phaseId": 0,
                    "submits": []
                }
            ],
            "results": [
                {
                    "objectId": 92,
                    "size": 200
                }
            ],
            "taskId": "4e7ca2b98ef74321b145d346af21aa02"
        },
        {
            "phases": [
                {
                    "creates": [],
                    "dependsOn": [
                        23,
                        24,
                        4,
                        93
                    ],
                    "duration": 44.47871708869934,
                    "phaseId": 0,
                    "submits": []
                }
            ],
            "results": [
                {
                    "objectId": 100,
                    "size": 200
                }
            ],
            "taskId": "470b6c27caa74fd9894a8bddae88faa0"
        },
        {
            "phases": [
                {
                    "creates": [],
                    "dependsOn": [
                        25,
                        26,
                        4,
                        101
                    ],
                    "duration": 45.80022096633911,
                    "phaseId": 0,
                    "submits": []
                }
            ],
            "results": [
                {
                    "objectId": 108,
                    "size": 200
                }
            ],
            "taskId": "f954519ed4304bc1a7228448136bb1c8"
        },
        {
            "phases": [
                {
                    "creates": [
                        {
                            "objectId": 27,
                            "size": 144,
                            "timeOffset": 0.0030291080474853516
                        },
                        {
                            "objectId": 29,
                            "size": 144,
                            "timeOffset": 0.009398937225341797
                        },
                        {
                            "objectId": 31,
                            "size": 88,
                            "timeOffset": 0.01708698272705078
                        }
                    ],
                    "dependsOn": [],
                    "duration": 0.019204139709472656,
                    "phaseId": 0,
                    "submits": [
                        {
                            "taskId": "e235c8d23feb40e4a922c3feaddde7bd",
                            "timeOffset": 0.004827022552490234
                        },
                        {
                            "taskId": "ceb226fa48c6474d8faf3466ec983d51",
                            "timeOffset": 0.011167049407958984
                        },
                        {
                            "taskId": "71938e011ec54fc6a5b9672c08d83bc3",
                            "timeOffset": 0.018902063369750977
                        }
                    ]
                },
                {
                    "creates": [
                        {
                            "objectId": 27,
                            "size": 144,
                            "timeOffset": 0.0030291080474853516
                        },
                        {
                            "objectId": 29,
                            "size": 144,
                            "timeOffset": 0.009398937225341797
                        },
                        {
                            "objectId": 31,
                            "size": 88,
                            "timeOffset": 0.01708698272705078
                        }
                    ],
                    "dependsOn": [],
                    "duration": 0.47823596000671387,
                    "phaseId": 0,
                    "submits": [
                        {
                            "taskId": "e235c8d23feb40e4a922c3feaddde7bd",
                            "timeOffset": 0.004827022552490234
                        },
                        {
                            "taskId": "ceb226fa48c6474d8faf3466ec983d51",
                            "timeOffset": 0.011167049407958984
                        },
                        {
                            "taskId": "71938e011ec54fc6a5b9672c08d83bc3",
                            "timeOffset": 0.018902063369750977
                        }
                    ]
                },
                {
                    "creates": [],
                    "dependsOn": [
                        32
                    ],
                    "duration": 0.006273031234741211,
                    "phaseId": 1,
                    "submits": []
                }
            ],
            "results": [
                {
                    "objectId": 4,
                    "size": 1572992
                }
            ],
            "taskId": "6b638df85f52414ea908c8b323e7138d"
        },
        {
            "phases": [
                {
                    "creates": [],
                    "dependsOn": [
                        23,
                        24,
                        4,
                        37
                    ],
                    "duration": 46.02612113952637,
                    "phaseId": 0,
                    "submits": []
                }
            ],
            "results": [
                {
                    "objectId": 39,
                    "size": 200
                }
            ],
            "taskId": "4abf9255553148adb791976dddc1ff21"
        },
        {
            "phases": [
                {
                    "creates": [],
                    "dependsOn": [
                        23,
                        24,
                        4,
                        45
                    ],
                    "duration": 45.50258803367615,
                    "phaseId": 0,
                    "submits": []
                }
            ],
            "results": [
                {
                    "objectId": 49,
                    "size": 200
                }
            ],
            "taskId": "97eda6a1d0a04fdeaae4e6f21c72f9bd"
        },
        {
            "phases": [
                {
                    "creates": [],
                    "dependsOn": [
                        25,
                        26,
                        4,
                        53
                    ],
                    "duration": 45.86783790588379,
                    "phaseId": 0,
                    "submits": []
                }
            ],
            "results": [
                {
                    "objectId": 59,
                    "size": 200
                }
            ],
            "taskId": "f9c0715becdf44629192d34b97c191d0"
        },
        {
            "phases": [
                {
                    "creates": [],
                    "dependsOn": [
                        23,
                        24,
                        4,
                        61
                    ],
                    "duration": 44.603830099105835,
                    "phaseId": 0,
                    "submits": []
                }
            ],
            "results": [
                {
                    "objectId": 63,
                    "size": 200
                }
            ],
            "taskId": "f09fb160074b4e698af7a872bb966072"
        },
        {
            "phases": [
                {
                    "creates": [],
                    "dependsOn": [
                        25,
                        26,
                        4,
                        69
                    ],
                    "duration": 44.800353050231934,
                    "phaseId": 0,
                    "submits": []
                }
            ],
            "results": [
                {
                    "objectId": 75,
                    "size": 200
                }
            ],
            "taskId": "be5ac2f2d4e24f1681e0143757a6d156"
        },
        {
            "phases": [
                {
                    "creates": [],
                    "dependsOn": [
                        25,
                        26,
                        4,
                        77
                    ],
                    "duration": 45.02034091949463,
                    "phaseId": 0,
                    "submits": []
                }
            ],
            "results": [
                {
                    "objectId": 84,
                    "size": 200
                }
            ],
            "taskId": "fcfa11e723f34e9ca47abe94443f8325"
        },
        {
            "phases": [
                {
                    "creates": [],
                    "dependsOn": [
                        23,
                        24,
                        4,
                        85
                    ],
                    "duration": 45.177711963653564,
                    "phaseId": 0,
                    "submits": []
                }
            ],
            "results": [
                {
                    "objectId": 91,
                    "size": 200
                }
            ],
            "taskId": "eb3614eda45f4fc986132a369670a445"
        },
        {
            "phases": [
                {
                    "creates": [],
                    "dependsOn": [
                        23,
                        24,
                        4,
                        93
                    ],
                    "duration": 45.867082834243774,
                    "phaseId": 0,
                    "submits": []
                }
            ],
            "results": [
                {
                    "objectId": 99,
                    "size": 200
                }
            ],
            "taskId": "c70b7a6122294025a9890cefd8497710"
        },
        {
            "phases": [
                {
                    "creates": [],
                    "dependsOn": [
                        23,
                        24,
                        4,
                        101
                    ],
                    "duration": 45.87528204917908,
                    "phaseId": 0,
                    "submits": []
                }
            ],
            "results": [
                {
                    "objectId": 105,
                    "size": 200
                }
            ],
            "taskId": "df87ddc7e6824e5cb1319034269f547e"
        },
        {
            "phases": [
                {
                    "creates": [],
                    "dependsOn": [],
                    "duration": 0.007391929626464844,
                    "phaseId": 0,
                    "submits": []
                }
            ],
            "results": [
                {
                    "objectId": 30,
                    "size": 1572992
                }
            ],
            "taskId": "ceb226fa48c6474d8faf3466ec983d51"
        },
        {
            "phases": [
                {
                    "creates": [],
                    "dependsOn": [
                        23,
                        24,
                        4,
                        37
                    ],
                    "duration": 46.10068917274475,
                    "phaseId": 0,
                    "submits": []
                }
            ],
            "results": [
                {
                    "objectId": 40,
                    "size": 200
                }
            ],
            "taskId": "1a8adc0f17884a28bffba2347ef426a2"
        },
        {
            "phases": [
                {
                    "creates": [],
                    "dependsOn": [
                        25,
                        26,
                        4,
                        45
                    ],
                    "duration": 45.559468030929565,
                    "phaseId": 0,
                    "submits": []
                }
            ],
            "results": [
                {
                    "objectId": 48,
                    "size": 200
                }
            ],
            "taskId": "a2ee2a0688e04b89808f9c9be20e1841"
        },
        {
            "phases": [
                {
                    "creates": [],
                    "dependsOn": [
                        23,
                        24,
                        4,
                        53
                    ],
                    "duration": 45.710192918777466,
                    "phaseId": 0,
                    "submits": []
                }
            ],
            "results": [
                {
                    "objectId": 58,
                    "size": 200
                }
            ],
            "taskId": "7510f632a5534d01b35d9bdfa882df53"
        },
        {
            "phases": [
                {
                    "creates": [],
                    "dependsOn": [
                        25,
                        26,
                        4,
                        61
                    ],
                    "duration": 45.21798396110535,
                    "phaseId": 0,
                    "submits": []
                }
            ],
            "results": [
                {
                    "objectId": 64,
                    "size": 200
                }
            ],
            "taskId": "b46bd7d4e1eb427e8f6ddee8eb74a6ce"
        },
        {
            "phases": [
                {
                    "creates": [],
                    "dependsOn": [
                        23,
                        24,
                        4,
                        69
                    ],
                    "duration": 44.82682800292969,
                    "phaseId": 0,
                    "submits": []
                }
            ],
            "results": [
                {
                    "objectId": 72,
                    "size": 200
                }
            ],
            "taskId": "a04dbc3ed086426e9aae5424e0e02c36"
        },
        {
            "phases": [
                {
                    "creates": [],
                    "dependsOn": [
                        25,
                        26,
                        4,
                        77
                    ],
                    "duration": 45.60258507728577,
                    "phaseId": 0,
                    "submits": []
                }
            ],
            "results": [
                {
                    "objectId": 82,
                    "size": 200
                }
            ],
            "taskId": "2c791430e21d48dea0a05f98c102d3ed"
        },
        {
            "phases": [
                {
                    "creates": [],
                    "dependsOn": [
                        23,
                        24,
                        4,
                        85
                    ],
                    "duration": 45.561179876327515,
                    "phaseId": 0,
                    "submits": []
                }
            ],
            "results": [
                {
                    "objectId": 89,
                    "size": 200
                }
            ],
            "taskId": "ce6a68fe828546c4b20f0f2f1bf07565"
        },
        {
            "phases": [
                {
                    "creates": [],
                    "dependsOn": [
                        25,
                        26,
                        4,
                        93
                    ],
                    "duration": 45.88948893547058,
                    "phaseId": 0,
                    "submits": []
                }
            ],
            "results": [
                {
                    "objectId": 97,
                    "size": 200
                }
            ],
            "taskId": "e5b03b43745e4c5594de454a42b7566f"
        },
        {
            "phases": [
                {
                    "creates": [],
                    "dependsOn": [
                        23,
                        24,
                        4,
                        101
                    ],
                    "duration": 45.65618705749512,
                    "phaseId": 0,
                    "submits": []
                }
            ],
            "results": [
                {
                    "objectId": 104,
                    "size": 200
                }
            ],
            "taskId": "799375bfdf3c41aeb0a3e19730cb2561"
        },
        {
            "phases": [
                {
                    "creates": [],
                    "dependsOn": [],
                    "duration": 0.0013270378112792969,
                    "phaseId": 0,
                    "submits": []
                }
            ],
            "results": [
                {
                    "objectId": 36,
                    "size": 88
                }
            ],
            "taskId": "5bb70285228548af9e520162e897eb94"
        },
        {
            "phases": [
                {
                    "creates": [],
                    "dependsOn": [
                        25,
                        26,
                        4,
                        37
                    ],
                    "duration": 45.77849507331848,
                    "phaseId": 0,
                    "submits": []
                }
            ],
            "results": [
                {
                    "objectId": 44,
                    "size": 200
                }
            ],
            "taskId": "aaca4eb03dbf4ae797217f6ac0939a50"
        },
        {
            "phases": [
                {
                    "creates": [],
                    "dependsOn": [
                        23,
                        24,
                        4,
                        45
                    ],
                    "duration": 45.85276794433594,
                    "phaseId": 0,
                    "submits": []
                }
            ],
            "results": [
                {
                    "objectId": 51,
                    "size": 200
                }
            ],
            "taskId": "ed31e420c9c74ffc95bce58190179129"
        },
        {
            "phases": [
                {
                    "creates": [],
                    "dependsOn": [
                        23,
                        24,
                        4,
                        53
                    ],
                    "duration": 45.70957684516907,
                    "phaseId": 0,
                    "submits": []
                }
            ],
            "results": [
                {
                    "objectId": 55,
                    "size": 200
                }
            ],
            "taskId": "506095e4b6b847cb9a88090865dfc0c6"
        },
        {
            "phases": [
                {
                    "creates": [],
                    "dependsOn": [
                        23,
                        24,
                        4,
                        61
                    ],
                    "duration": 44.61800193786621,
                    "phaseId": 0,
                    "submits": []
                }
            ],
            "results": [
                {
                    "objectId": 65,
                    "size": 200
                }
            ],
            "taskId": "c7a0061d87a24fc790dd7ae1da132676"
        },
        {
            "phases": [
                {
                    "creates": [],
                    "dependsOn": [
                        25,
                        26,
                        4,
                        69
                    ],
                    "duration": 45.3296480178833,
                    "phaseId": 0,
                    "submits": []
                }
            ],
            "results": [
                {
                    "objectId": 74,
                    "size": 200
                }
            ],
            "taskId": "ae297a0d676345a4a35d77736f1fb057"
        },
        {
            "phases": [
                {
                    "creates": [],
                    "dependsOn": [
                        23,
                        24,
                        4,
                        77
                    ],
                    "duration": 45.284388065338135,
                    "phaseId": 0,
                    "submits": []
                }
            ],
            "results": [
                {
                    "objectId": 80,
                    "size": 200
                }
            ],
            "taskId": "57041dfd111440bf9364fadc81385f0e"
        },
        {
            "phases": [
                {
                    "creates": [],
                    "dependsOn": [
                        23,
                        24,
                        4,
                        85
                    ],
                    "duration": 45.599807024002075,
                    "phaseId": 0,
                    "submits": []
                }
            ],
            "results": [
                {
                    "objectId": 90,
                    "size": 200
                }
            ],
            "taskId": "2d7cdb8215804b9e890ee613f6ca2fa0"
        },
        {
            "phases": [
                {
                    "creates": [],
                    "dependsOn": [
                        25,
                        26,
                        4,
                        93
                    ],
                    "duration": 45.739100217819214,
                    "phaseId": 0,
                    "submits": []
                }
            ],
            "results": [
                {
                    "objectId": 96,
                    "size": 200
                }
            ],
            "taskId": "ecf37c92c5cc44828164ae3a9b630e72"
        },
        {
            "phases": [
                {
                    "creates": [],
                    "dependsOn": [
                        25,
                        26,
                        4,
                        101
                    ],
                    "duration": 45.958802938461304,
                    "phaseId": 0,
                    "submits": []
                }
            ],
            "results": [
                {
                    "objectId": 106,
                    "size": 200
                }
            ],
            "taskId": "5f11921148a04180a5e881825fb9f1f9"
        }
    ]
}